apmodel/__init__.py
apmodel/_version.py
apmodel/context.py
apmodel/loader.py
apmodel/registry.py
apmodel/types.py
apmodel/_core/key.py
apmodel/_core/_initial/_rebuild.py
apmodel/_core/_initial/_registry_bootstrap.py
apmodel/_core/_jsonjd/loader.py
apmodel/_core/_jsonjd/_preloads/as2.jsonld
apmodel/_core/_jsonjd/_preloads/litepub-0.1.jsonld
apmodel/_core/_jsonjd/_preloads/schemaorg.jsonld
apmodel/_core/_jsonjd/_preloads/security-v1.jsonld
apmodel/core/__init__.py
apmodel/core/activity.py
apmodel/core/collection.py
apmodel/core/link.py
apmodel/core/object.py
apmodel/extra/__init__.py
apmodel/extra/emoji.py
apmodel/extra/hashtag.py
apmodel/extra/cid/__init__.py
apmodel/extra/cid/data_integrity_proof.py
apmodel/extra/cid/multikey.py
apmodel/extra/litepub/__init__.py
apmodel/extra/litepub/emoji_react.py
apmodel/extra/schema/__init__.py
apmodel/extra/schema/propertyvalue.py
apmodel/extra/security/__init__.py
apmodel/extra/security/cryptographickey.py
apmodel/nodeinfo/__init__.py
apmodel/nodeinfo/nodeinfo.py
apmodel/vocab/__init__.py
apmodel/vocab/actor.py
apmodel/vocab/article.py
apmodel/vocab/document.py
apmodel/vocab/event.py
apmodel/vocab/mention.py
apmodel/vocab/note.py
apmodel/vocab/profile.py
apmodel/vocab/tombstone.py
apmodel/vocab/activity/__init__.py
apmodel/vocab/activity/accept.py
apmodel/vocab/activity/add.py
apmodel/vocab/activity/announce.py
apmodel/vocab/activity/arrive.py
apmodel/vocab/activity/block.py
apmodel/vocab/activity/create.py
apmodel/vocab/activity/delete.py
apmodel/vocab/activity/dislike.py
apmodel/vocab/activity/flag.py
apmodel/vocab/activity/follow.py
apmodel/vocab/activity/ignore.py
apmodel/vocab/activity/invite.py
apmodel/vocab/activity/join.py
apmodel/vocab/activity/leave.py
apmodel/vocab/activity/like.py
apmodel/vocab/activity/listen.py
apmodel/vocab/activity/move.py
apmodel/vocab/activity/offer.py
apmodel/vocab/activity/question.py
apmodel/vocab/activity/read.py
apmodel/vocab/activity/reject.py
apmodel/vocab/activity/remove.py
apmodel-0.5.2.dist-info/METADATA
apmodel-0.5.2.dist-info/WHEEL
apmodel-0.5.2.dist-info/entry_points.txt
apmodel-0.5.2.dist-info/licenses/LICENSE
apmodel-0.5.2.dist-info/RECORD
