Metadata-Version: 2.4
Name: apmodel
Version: 0.5.2
Summary: ActivityStreams 2.0 and nodeinfo 2.0/2.1 implementation for Python.
Project-URL: Repository, https://github.com/fedi-libs/apmodel
Project-URL: Issues, https://github.com/fedi-libs/apmodel/issues
Project-URL: Changelog, https://github.com/fedi-libs/apmodel/blob/main/CHANGELOG.md
Author-email: AmaseCocoa <cocoa@amase.cc>
License: MIT
License-File: LICENSE
Classifier: Development Status :: 2 - Pre-Alpha
Classifier: Programming Language :: Python :: 3.10
Classifier: Programming Language :: Python :: 3.11
Classifier: Programming Language :: Python :: 3.12
Classifier: Programming Language :: Python :: 3.13
Requires-Python: >=3.10
Requires-Dist: cryptography>=45.0.6
Requires-Dist: multiformats>=0.3.1.post4
Requires-Dist: pydantic>=2.12.5
Requires-Dist: pyld[aiohttp,requests]>=2.0.4
Requires-Dist: typing-extensions>=4.15.0
